dovado.py
setup.cfg
setup.py
dovado.egg-info/PKG-INFO
dovado.egg-info/SOURCES.txt
dovado.egg-info/dependency_links.txt
dovado.egg-info/requires.txt
dovado.egg-info/top_level.txt