Metadata-Version: 1.1
Name: dovado
Version: 0.4.1
Summary: Communicate with Dovado router
Home-page: https://github.com/molobrakos/dovado
Author: Erik
Author-email: Erik
License: UNKNOWN
Platform: UNKNOWN
Provides: dovado
